pigeon/__init__.py
pigeon/client.py
pigeon/exceptions.py
pigeon/sync_client.py
pigeon/types.py
roselabs_pigeon-0.1.2.dist-info/METADATA
roselabs_pigeon-0.1.2.dist-info/WHEEL
roselabs_pigeon-0.1.2.dist-info/RECORD
