Metadata-Version: 2.4
Name: roselabs-pigeon
Version: 0.1.2
Summary: Pigeon transactional email SDK for Python
Project-URL: Homepage, https://pigeon.roselabs.io
Project-URL: Repository, https://github.com/roselabs/pigeon-sdk-python
Project-URL: Documentation, https://pigeon.roselabs.io/docs
Author-email: RoseLabs <support@roselabs.io>
License-Expression: MIT
Keywords: email,email-api,email-templates,pigeon,roselabs,transactional-email
Classifier: Development Status :: 4 - Beta
Classifier: Intended Audience :: Developers
Classifier: License :: OSI Approved :: MIT License
Classifier: Programming Language :: Python :: 3
Classifier: Programming Language :: Python :: 3.9
Classifier: Programming Language :: Python :: 3.10
Classifier: Programming Language :: Python :: 3.11
Classifier: Programming Language :: Python :: 3.12
Classifier: Topic :: Communications :: Email
Classifier: Topic :: Software Development :: Libraries :: Python Modules
Requires-Python: >=3.9
Requires-Dist: httpx>=0.25.0
Provides-Extra: dev
Requires-Dist: pytest-asyncio>=0.21.0; extra == 'dev'
Requires-Dist: pytest>=7.0.0; extra == 'dev'
Requires-Dist: ruff>=0.1.0; extra == 'dev'
